nl2flow/__init__.py
nl2flow/compile/__init_.py
nl2flow/compile/compilations.py
nl2flow/compile/flow.py
nl2flow/compile/operators.py
nl2flow/compile/options.py
nl2flow/compile/schemas.py
nl2flow/compile/utils.py
nl2flow/compile/basic_compilations/__init__.py
nl2flow/compile/basic_compilations/compile_confirmation.py
nl2flow/compile/basic_compilations/compile_constraints.py
nl2flow/compile/basic_compilations/compile_goals.py
nl2flow/compile/basic_compilations/compile_history.py
nl2flow/compile/basic_compilations/compile_labels.py
nl2flow/compile/basic_compilations/compile_mappings.py
nl2flow/compile/basic_compilations/compile_operators.py
nl2flow/compile/basic_compilations/compile_slots.py
nl2flow/compile/basic_compilations/utils.py
nl2flow/compile/basic_compilations/compile_references/compile_reference_basic.py
nl2flow/compile/basic_compilations/compile_references/compile_reference_tokenize.py
nl2flow/compile/basic_compilations/compile_references/utils.py
nl2flow/debug/__init__.py
nl2flow/debug/debug.py
nl2flow/debug/schemas.py
nl2flow/plan/__init__.py
nl2flow/plan/options.py
nl2flow/plan/planner.py
nl2flow/plan/schemas.py
nl2flow/plan/utils.py
nl2flow/plan/planners/kstar.py
nl2flow/printers/__init__.py
nl2flow/printers/codelike.py
nl2flow/printers/driver.py
nl2flow/printers/explain.py
nl2flow/printers/verbalize.py
nl2flow/services/__init__.py
nl2flow/services/sketch.py
nl2flow/services/compilations/catalog_compilations.py
nl2flow/services/compilations/sketch_compilations.py
nl2flow/services/schemas/__init__.py
nl2flow/services/schemas/sketch_options.py
nl2flow/services/schemas/sketch_schemas.py
nl2flow/utility/__init__.py
nl2flow/utility/file_utility.py
nl2flow-0.1.3.dist-info/licenses/LICENSE
profiler/__init__.py
profiler/common_helpers/hash_helper.py
profiler/common_helpers/string_helper.py
profiler/common_helpers/time_helper.py
profiler/converters/__init__.py
profiler/converters/info_2_flow_converter.py
profiler/data/__init__.py
profiler/data/api_spec_data.py
nl2flow-0.1.3.dist-info/METADATA
nl2flow-0.1.3.dist-info/WHEEL
nl2flow-0.1.3.dist-info/top_level.txt
nl2flow-0.1.3.dist-info/RECORD
