Metadata-Version: 2.4
Name: nl2flow
Version: 0.1.3
Summary: NL2Flow: A PDDL interface to flow construction
Author-email: Tathagata Chakraborti <tchakra2@ibm.com>, Jungkoo Kang <jungkoo.kang@gmail.com>
Maintainer-email: Tathagata Chakraborti <tchakra2@ibm.com>, Jungkoo Kang <jungkoo.kang@gmail.com>
License:                                  Apache License
Project-URL: Homepage, https://github.com/IBM/nl2flow
Project-URL: Bug Reports, https://github.com/IBM/nl2flow/issues
Project-URL: Funding, https://research.ibm.com
Project-URL: Say Thanks!, https://tchakra2.com
Project-URL: Source, https://github.com/IBM/nl2flow
Keywords: automated planning,natural language processing,process automation,service composition,conversational agents,generative ai,large language models
Classifier: Development Status :: 2 - Pre-Alpha
Classifier: Intended Audience :: Developers
Classifier: Intended Audience :: Science/Research
Classifier: Natural Language :: English
Classifier: License :: OSI Approved :: Apache Software License
Classifier: Operating System :: MacOS
Classifier: Operating System :: Unix
Classifier: Programming Language :: Python :: 3.11
Classifier: Framework :: Pydantic :: 2
Classifier: Framework :: Pytest
Classifier: Topic :: Scientific/Engineering :: Artificial Intelligence
Classifier: Topic :: Scientific/Engineering :: Human Machine Interfaces
Classifier: Topic :: Scientific/Engineering :: Information Analysis
Classifier: Topic :: Software Development :: User Interfaces
Requires-Python: >=3.10
License-File: LICENSE
Requires-Dist: pydantic
Requires-Dist: pyyaml
Requires-Dist: tarski-tmp
Requires-Dist: StrEnum
Requires-Dist: kstar-planner
Requires-Dist: haikunator
Requires-Dist: nestful-wrapper
Provides-Extra: dev
Requires-Dist: check-manifest; extra == "dev"
Requires-Dist: pytest; extra == "dev"
Requires-Dist: pytest-mock; extra == "dev"
Requires-Dist: black; extra == "dev"
Requires-Dist: pylint; extra == "dev"
Requires-Dist: flake8; extra == "dev"
Requires-Dist: pre-commit; extra == "dev"
Requires-Dist: Flake8-pyproject; extra == "dev"
Requires-Dist: coverage; extra == "dev"
Requires-Dist: pytest-mock; extra == "dev"
Requires-Dist: types-PyYAML; extra == "dev"
Dynamic: license-file
